src/__init__.py
src/__main__.py
src/bundle.py
src/foreman.py
src/img3.py
src/img4.py
src/iphonewiki.py
src/ipsw.py
src/ipswapi.py
src/manifest.py
src/template.py
src/tss.py
src/usb.py
src/utils.py
iospytools-1.0.6.dist-info/LICENSE.txt
iospytools-1.0.6.dist-info/METADATA
iospytools-1.0.6.dist-info/WHEEL
iospytools-1.0.6.dist-info/entry_points.txt
iospytools-1.0.6.dist-info/top_level.txt
iospytools-1.0.6.dist-info/RECORD
