Metadata-Version: 2.1
Name: iospytools
Version: 1.0.6
Summary: provides useful tools/commands which are used in iOS research
Home-page: https://github.com/merculous/ios-python-tools
Author: Merculous
Author-email: vycemerculous@gmail.com
License: UNKNOWN
Platform: UNKNOWN
Classifier: Programming Language :: Python :: 3
Classifier: Programming Language :: Python :: 3.5
Classifier: Programming Language :: Python :: 3.6
Classifier: Programming Language :: Python :: 3.7
Classifier: Programming Language :: Python :: 3.8
Classifier: License :: OSI Approved :: GNU General Public License v3 (GPLv3)
Requires-Python: >=3.5
Requires-Dist: autopep8 (==1.5.3)
Requires-Dist: bsdiff4 (==1.1.9)
Requires-Dist: certifi (==2020.6.20)
Requires-Dist: chardet (==3.0.4)
Requires-Dist: flake8 (==3.8.3)
Requires-Dist: humanize (==2.5.0)
Requires-Dist: idna (==2.10)
Requires-Dist: importlib-metadata (==1.7.0)
Requires-Dist: mccabe (==0.6.1)
Requires-Dist: progressbar (==2.5)
Requires-Dist: pycodestyle (==2.6.0)
Requires-Dist: pyflakes (==2.2.0)
Requires-Dist: pyusb (==1.0.2)
Requires-Dist: remotezip (==0.9.2)
Requires-Dist: requests (==2.24.0)
Requires-Dist: tabulate (==0.8.7)
Requires-Dist: toml (==0.10.1)
Requires-Dist: urllib3 (==1.25.9)
Requires-Dist: zipp (==1.2.0)
